skype_chatbot/__init__.py
skype_chatbot/skype_chatbot.py
skype_chatbot-1.0.4.dist-info/DESCRIPTION.rst
skype_chatbot-1.0.4.dist-info/METADATA
skype_chatbot-1.0.4.dist-info/RECORD
skype_chatbot-1.0.4.dist-info/WHEEL
skype_chatbot-1.0.4.dist-info/metadata.json
skype_chatbot-1.0.4.dist-info/top_level.txt
