Metadata-Version: 1.1
Name: skype_chatbot
Version: 1.0.4
Summary: API for development the Skype chat-bot
Home-page: UNKNOWN
Author: Anton Kotseruba
Author-email: ghost8recon@gmail.com
License: MIT
Keywords: skype chat-bot chatbot bot api
Platform: UNKNOWN
Classifier: Development Status :: 4 - Beta
Classifier: License :: OSI Approved :: MIT License
Classifier: Programming Language :: Python :: 3.6
Classifier: Topic :: Software Development :: Libraries :: Python Modules
